dickgen/__init__.py
dickgen/client.py
dickgen/lib/__init__.py
dickgen/lib/util/__init__.py
dickgen/lib/util/headers.py
dickgen/lib/util/helpers.py
dickgen-0.4.dist-info/METADATA
dickgen-0.4.dist-info/WHEEL
dickgen-0.4.dist-info/top_level.txt
dickgen-0.4.dist-info/RECORD
