Metadata-Version: 2.1
Name: dickgen
Version: 0.4
Author: yato
Author-email: ptimer60@gmail.com
License: MIT
Keywords: dickgen
Requires-Python: >=3.6
Requires-Dist: requests
Requires-Dist: bs4
Requires-Dist: setuptools
